{"result/failure_reason":"","_timestamp":1.7794388578042529e+09,"live/is_frozen":0,"live/nearest_ped_dist_m":5.86459752115225,"result/elapsed_sec":54.87,"live/path_deviation_m":0.1351805621962492,"result/total_freeze_sec":2,"_wandb":{"runtime":53},"live/angular_velocity_rps":-0.75,"live/linear_velocity_mps":0.8262635495072809,"result/success":1,"live/is_aligning_mode":1,"live/cumul_freeze_sec":1.996274471282959,"result/avg_solver_ms":3.12,"result/stop_go_count":1,"_runtime":53,"result/avg_v_mps":1.146,"result/avg_abs_w_rps":0.32,"live/elapsed_sec":54.86282253265381,"live/ped_blocking":0,"result/ped_clearance_m":0.327,"result/path_dev_max_m":0.667,"result/path_dev_mean_m":0.228,"live/solver_ms":71.78520799971011,"result/avg_recovery_latency_sec":-1,"_step":264}